{
  "kind": "collectionType",
  "collectionName": "articles",
  "info": {
    "singularName": "article",
    "pluralName": "articles",
    "displayName": "article",
    "description": ""
  },
  "options": {
    "draftAndPublish": true
  },
  "pluginOptions": {},
  "attributes": {
    "title": {
      "type": "string"
    },
    "author": {
      "type": "string"
    },
    "link": {
      "type": "string"
    },
    "date": {
      "type": "date"
    },
    "notes": {
      "type": "text"
    },
    "topics": {
      "type": "json"
    },
    "email": {
      "type": "email"
    },
    "type": {
      "type": "json"
    }
  }
}
